fuel_efficency/__init__.py
fuel_efficency/algorithms/__init__.py
fuel_efficency/algorithms/a_star.py
fuel_efficency/algorithms/context.py
fuel_efficency/algorithms/dijkstra.py
fuel_efficency/algorithms/path_finding.py
fuel_efficency/entities/__init__.py
fuel_efficency/entities/down_hill.py
fuel_efficency/entities/node.py
fuel_efficency/entities/plateau.py
fuel_efficency/entities/position.py
fuel_efficency/entities/up_hill.py
fuel_efficency/entities/valley.py
tests/__init__.py
tests/test_algorithms.py
tests/test_entities.py
tests/test_entities_raise.py
bees_exam-0.1.0.dist-info/METADATA
bees_exam-0.1.0.dist-info/WHEEL
bees_exam-0.1.0.dist-info/entry_points.txt
bees_exam-0.1.0.dist-info/top_level.txt
bees_exam-0.1.0.dist-info/RECORD
