Metadata-Version: 2.1
Name: bees-exam
Version: 0.1.0
Summary: UNKNOWN
Home-page: UNKNOWN
Author: Rodolfo Lotte
Author-email: rodolfo.lotte@email.com
License: UNKNOWN
Platform: UNKNOWN
